xypy.py
xypy-0.0.7.dist-info/LICENSE
xypy-0.0.7.dist-info/METADATA
xypy-0.0.7.dist-info/WHEEL
xypy-0.0.7.dist-info/top_level.txt
xypy-0.0.7.dist-info/RECORD
