Metadata-Version: 2.1
Name: xypy
Version: 0.0.7
Summary: A simulation framework for supervised learning data. The functionalities are specifically                   designed to let the user a maximum degrees of freedom, to ultimately fulfill the research purpose.                   Furthermore, feature importances of the simulation can be created on a local and a global level.                    This is particular interesting, for instance, to benchmark feature selection algorithms.
Home-page: http://github.com/andrebleier/XyPy
Author: André Bleier
Author-email: andrebleier@live.de
License: MIT
Keywords: simulation machine learning supervised feature selection
Platform: UNKNOWN
Classifier: Development Status :: 3 - Alpha
Classifier: Operating System :: OS Independent
Classifier: License :: OSI Approved :: MIT License  
Classifier: Programming Language :: Python :: 3
Classifier: Topic :: Scientific/Engineering :: Artificial Intelligence  
Requires-Dist: scipy
Requires-Dist: numpy
Requires-Dist: pandas
Requires-Dist: seaborn
Requires-Dist: matplotlib
Requires-Dist: statsmodels
Requires-Dist: sklearn
